README.md
setup.py
hnap_redis/__init__.py
hnap_redis.egg-info/PKG-INFO
hnap_redis.egg-info/SOURCES.txt
hnap_redis.egg-info/dependency_links.txt
hnap_redis.egg-info/requires.txt
hnap_redis.egg-info/top_level.txt