Metadata-Version: 2.1
Name: hnap-redis
Version: 0.3
Summary: Libreria para manejo sencillo de redis
Home-page: https://git.hospitalposadas.gob.ar/31258287/hnap_redis
Author: Pablo Padulles
Author-email: padulles.pablo@hospitalposadas.gob.ar
License: UNKNOWN
Platform: UNKNOWN
Classifier: Programming Language :: Python :: 3
Classifier: License :: OSI Approved :: MIT License
Classifier: Operating System :: OS Independent
Requires-Python: >=3.6
